[
  {
    "date": "2026-07-19",
    "theme": "雨",
    "title": "Falling Rain",
    "keyframes_css": "@keyframes fall {\n  0% {\n    transform: translateY(-10px);\n    opacity: 1;\n  }\n  90% {\n    opacity: 1;\n  }\n  100% {\n    transform: translateY(200px);\n    opacity: 0;\n  }\n}\n\n.demo-stage {\n  width: 200px;\n  height: 200px;\n  background: linear-gradient(180deg, #2c3e50 0%, #34495e 100%);\n  overflow: hidden;\n  position: relative;\n}\n\n.demo-stage::before,\n.demo-stage::after {\n  content: '';\n  position: absolute;\n  width: 2px;\n  height: 10px;\n  background: #ecf0f1;\n  animation: fall 1s infinite linear;\n}\n\n.demo-stage::before {\n  left: 30px;\n  animation-delay: 0s;\n}\n\n.demo-stage::after {\n  left: 80px;\n  animation-delay: 0.3s;\n}\n\n.demo-stage .rain1 {\n  position: absolute;\n  width: 2px;\n  height: 10px;\n  background: #ecf0f1;\n  animation: fall 1.2s infinite linear;\n}\n\n.demo-stage .rain1:nth-child(1) {\n  left: 50px;\n  animation-delay: 0.1s;\n}\n\n.demo-stage .rain1:nth-child(2) {\n  left: 120px;\n  animation-delay: 0.5s;\n}\n\n.demo-stage .rain1:nth-child(3) {\n  left: 150px;\n  animation-delay: 0.8s;\n}",
    "demo_html": "<div class=\"rain1\"></div><div class=\"rain1\"></div><div class=\"rain1\"></div>"
  },
  {
    "date": "2026-07-18",
    "theme": "振り子",
    "title": "振り子のゆらぎ",
    "keyframes_css": "@keyframes swing {\n  0% {\n    transform: rotate(0deg);\n  }\n  25% {\n    transform: rotate(45deg);\n  }\n  50% {\n    transform: rotate(0deg);\n  }\n  75% {\n    transform: rotate(-45deg);\n  }\n  100% {\n    transform: rotate(0deg);\n  }\n}\n\n.demo-stage {\n  width: 200px;\n  height: 200px;\n  display: flex;\n  align-items: flex-start;\n  justify-content: center;\n  padding-top: 10px;\n  background: linear-gradient(135deg, #667eea 0%, #764ba2 100%);\n}\n\n.demo-stage .pendulum-container {\n  position: relative;\n  width: 100px;\n  height: 150px;\n  display: flex;\n  justify-content: center;\n}\n\n.demo-stage .pivot {\n  position: absolute;\n  top: 0;\n  width: 12px;\n  height: 12px;\n  background: #fff;\n  border-radius: 50%;\n  z-index: 10;\n}\n\n.demo-stage .rod {\n  position: absolute;\n  top: 6px;\n  left: 50%;\n  width: 4px;\n  height: 100px;\n  background: #fff;\n  transform-origin: top center;\n  animation: swing 2s ease-in-out infinite;\n}\n\n.demo-stage .bob {\n  position: absolute;\n  bottom: 0;\n  left: 50%;\n  transform: translateX(-50%);\n  width: 20px;\n  height: 20px;\n  background: #ffd700;\n  border-radius: 50%;\n  box-shadow: 0 2px 8px rgba(0, 0, 0, 0.3);\n}",
    "demo_html": "<div class=\"pendulum-container\">\n  <div class=\"pivot\"></div>\n  <div class=\"rod\">\n    <div class=\"bob\"></div>\n  </div>\n</div>"
  },
  {
    "date": "2026-07-17",
    "theme": "地層",
    "title": "地層の堆積",
    "keyframes_css": "@keyframes settle {\n  0% {\n    transform: translateY(-200px);\n    opacity: 0;\n  }\n  10% {\n    opacity: 1;\n  }\n  90% {\n    opacity: 1;\n  }\n  100% {\n    transform: translateY(0);\n    opacity: 1;\n  }\n}\n\n@keyframes shift {\n  0%, 100% {\n    transform: translateX(0);\n  }\n  50% {\n    transform: translateX(2px);\n  }\n}\n\n.demo-stage {\n  width: 200px;\n  height: 200px;\n  background: linear-gradient(180deg, #87CEEB 0%, #E0F6FF 100%);\n  position: relative;\n  overflow: hidden;\n  border-radius: 4px;\n}\n\n.demo-stage .layer {\n  position: absolute;\n  width: 100%;\n  height: 30px;\n  animation: settle 3s ease-in forwards, shift 2s ease-in-out infinite;\n}\n\n.demo-stage .layer:nth-child(1) {\n  background: linear-gradient(90deg, #8B7355 0%, #A0826D 100%);\n  animation-delay: 0s, 0s;\n  top: 10px;\n}\n\n.demo-stage .layer:nth-child(2) {\n  background: linear-gradient(90deg, #D2B48C 0%, #DEB887 100%);\n  animation-delay: 0.6s, 0.6s;\n  top: 40px;\n}\n\n.demo-stage .layer:nth-child(3) {\n  background: linear-gradient(90deg, #A9A9A9 0%, #C0C0C0 100%);\n  animation-delay: 1.2s, 1.2s;\n  top: 70px;\n}\n\n.demo-stage .layer:nth-child(4) {\n  background: linear-gradient(90deg, #CD853F 0%, #DEB887 100%);\n  animation-delay: 1.8s, 1.8s;\n  top: 100px;\n}\n\n.demo-stage .layer:nth-child(5) {\n  background: linear-gradient(90deg, #696969 0%, #808080 100%);\n  animation-delay: 2.4s, 2.4s;\n  top: 130px;\n}\n\n.demo-stage .layer:nth-child(6) {\n  background: linear-gradient(90deg, #8B4513 0%, #A0522D 100%);\n  animation-delay: 3s, 3s;\n  top: 160px;\n}",
    "demo_html": "<div class=\"layer\"></div>\n<div class=\"layer\"></div>\n<div class=\"layer\"></div>\n<div class=\"layer\"></div>\n<div class=\"layer\"></div>\n<div class=\"layer\"></div>"
  },
  {
    "date": "2026-07-17",
    "theme": "蝉",
    "title": "夏の蝉",
    "keyframes_css": "@keyframes cicadaWing {\n  0%, 100% { transform: scaleX(1) skewY(0deg); opacity: 0.55; }\n  50% { transform: scaleX(1.08) skewY(2deg); opacity: 0.75; }\n}\n@keyframes cicadaBody {\n  0%, 100% { transform: translateY(0px) rotate(-2deg); }\n  40% { transform: translateY(-3px) rotate(-2deg); }\n  70% { transform: translateY(1px) rotate(-2deg); }\n}\n@keyframes shimmer {\n  0%, 100% { opacity: 0.18; transform: translateX(0px) translateY(0px); }\n  50% { opacity: 0.38; transform: translateX(4px) translateY(-3px); }\n}\n@keyframes leafSway {\n  0%, 100% { transform: rotate(8deg) translateY(0px); }\n  50% { transform: rotate(11deg) translateY(-4px); }\n}\n\n.demo-stage {\n  width: 200px;\n  height: 200px;\n  position: relative;\n  overflow: hidden;\n  background: linear-gradient(160deg, #eceae3 0%, #e4e8dc 60%, #dde6d0 100%);\n}\n\n/* 木の幹 */\n.demo-stage .trunk {\n  position: absolute;\n  bottom: 0;\n  left: 78px;\n  width: 22px;\n  height: 160px;\n  background: linear-gradient(to right, #c8b89a, #d9c8a8, #bfa880);\n  border-radius: 10px 8px 6px 6px;\n}\n.demo-stage .trunk::before {\n  content: '';\n  position: absolute;\n  left: 3px;\n  top: 20px;\n  width: 6px;\n  height: 80px;\n  background: rgba(160,130,90,0.35);\n  border-radius: 4px;\n}\n\n/* 葉 */\n.demo-stage .leaf {\n  position: absolute;\n  width: 52px;\n  height: 28px;\n  background: linear-gradient(130deg, #a0c878, #7ab858, #8ec870);\n  border-radius: 50% 80% 50% 20%;\n  box-shadow: inset 0 2px 4px rgba(100,160,60,0.3);\n  animation: leafSway 3.8s ease-in-out infinite;\n  transform-origin: left center;\n}\n.demo-stage .leaf:nth-child(2) {\n  top: 32px;\n  left: 86px;\n  transform: rotate(8deg);\n  animation-delay: 0s;\n}\n.demo-stage .leaf:nth-child(3) {\n  top: 54px;\n  left: 44px;\n  transform: rotate(-140deg) scaleY(0.85);\n  animation-delay: 0.6s;\n  background: linear-gradient(130deg, #90bc68, #6aaa48);\n}\n.demo-stage .leaf:nth-child(4) {\n  top: 80px;\n  left: 94px;\n  transform: rotate(20deg) scaleX(0.8);\n  animation-delay: 1.1s;\n}\n\n/* 蝉 本体 */\n.demo-stage .cicada {\n  position: absolute;\n  top: 78px;\n  left: 68px;\n  width: 44px;\n  height: 26px;\n  animation: cicadaBody 2.4s ease-in-out infinite;\n}\n\n/* 腹部(胴体) */\n.demo-stage .cicada-body {\n  position: absolute;\n  bottom: 0;\n  left: 10px;\n  width: 22px;\n  height: 22px;\n  background: linear-gradient(170deg, #8a7858, #6e6040, #7a6848);\n  border-radius: 40% 40% 55% 55%;\n  box-shadow: 0 2px 4px rgba(80,60,20,0.25);\n}\n.demo-stage .cicada-body::before {\n  content: '';\n  position: absolute;\n  top: 3px;\n  left: 3px;\n  width: 16px;\n  height: 8px;\n  background: linear-gradient(to bottom, #b8a070, #a08858);\n  border-radius: 50%;\n  opacity: 0.7;\n}\n.demo-stage .cicada-body::after {\n  content: '';\n  position: absolute;\n  top: 12px;\n  left: 5px;\n  width: 12px;\n  height: 3px;\n  background: repeating-linear-gradient(to right, #6e5830 0px, #6e5830 2px, #907848 2px, #907848 4px);\n  border-radius: 2px;\n  opacity: 0.8;\n}\n\n/* 頭部 */\n.demo-stage .cicada-head {\n  position: absolute;\n  top: 4px;\n  left: 12px;\n  width: 14px;\n  height: 11px;\n  background: linear-gradient(160deg, #786448, #5a4c30);\n  border-radius: 50% 50% 40% 40%;\n  box-shadow: 0 1px 3px rgba(60,40,10,0.3);\n}\n.demo-stage .cicada-head::before {\n  content: '';\n  position: absolute;\n  top: 3px;\n  left: 2px;\n  width: 4px;\n  height: 4px;\n  background: #d0b870;\n  border-radius: 50%;\n  box-shadow: 6px 0 0 #d0b870;\n}\n\n/* 翅(左) */\n.demo-stage .wing-left {\n  position: absolute;\n  top: 0px;\n  left: -8px;\n  width: 32px;\n  height: 20px;\n  background: linear-gradient(120deg, rgba(200,220,255,0.62), rgba(180,210,240,0.45));\n  border-radius: 70% 30% 60% 20%;\n  box-shadow: inset 0 1px 2px rgba(150,180,220,0.4), 0 1px 3px rgba(120,150,200,0.15);\n  border: 1px solid rgba(160,190,230,0.45);\n  transform-origin: right center;\n  animation: cicadaWing 2.4s ease-in-out infinite;\n}\n.demo-stage .wing-left::before {\n  content: '';\n  position: absolute;\n  top: 3px;\n  left: 4px;\n  width: 20px;\n  height: 9px;\n  background: transparent;\n  border-radius: 60% 20% 50% 20%;\n  border: 1px solid rgba(150,185,230,0.35);\n}\n\n/* 翅(右) */\n.demo-stage .wing-right {\n  position: absolute;\n  top: 0px;\n  left: 18px;\n  width: 32px;\n  height: 20px;\n  background: linear-gradient(60deg, rgba(200,220,255,0.62), rgba(180,210,240,0.45));\n  border-radius: 30% 70% 20% 60%;\n  box-shadow: inset 0 1px 2px rgba(150,180,220,0.4), 0 1px 3px rgba(120,150,200,0.15);\n  border: 1px solid rgba(160,190,230,0.45);\n  transform-origin: left center;\n  animation: cicadaWing 2.4s ease-in-out infinite;\n  animation-delay: 0.05s;\n}\n.demo-stage .wing-right::before {\n  content: '';\n  position: absolute;\n  top: 3px;\n  left: 6px;\n  width: 20px;\n  height: 9px;\n  background: transparent;\n  border-radius: 20% 60% 20% 50%;\n  border: 1px solid rgba(150,185,230,0.35);\n}\n\n/* 光の粒 */\n.demo-stage .shimmer {\n  position: absolute;\n  border-radius: 50%;\n  background: rgba(255,240,180,0.55);\n  animation: shimmer 3s ease-in-out infinite;\n}\n.demo-stage .shimmer:nth-of-type(1) {\n  width: 7px; height: 7px;\n  top: 22px; left: 138px;\n  animation-delay: 0s;\n}\n.demo-stage .shimmer:nth-of-type(2) {\n  width: 4px; height: 4px;\n  top: 140px; left: 40px;\n  animation-delay: 1.2s;\n}\n.demo-stage .shimmer:nth-of-type(3) {\n  width: 5px; height: 5px;\n  top: 168px; left: 155px;\n  animation-delay: 2s;\n}",
    "demo_html": "<div class=\"demo-stage\">\n  <div class=\"trunk\"></div>\n  <div class=\"leaf\"></div>\n  <div class=\"leaf\"></div>\n  <div class=\"leaf\"></div>\n  <div class=\"cicada\">\n    <div class=\"wing-left\"></div>\n    <div class=\"wing-right\"></div>\n    <div class=\"cicada-body\"></div>\n    <div class=\"cicada-head\"></div>\n  </div>\n  <div class=\"shimmer\"></div>\n  <div class=\"shimmer\"></div>\n  <div class=\"shimmer\"></div>\n</div>"
  },
  {
    "date": "2026-07-16",
    "theme": "波",
    "title": "波のひとひら",
    "keyframes_css": "@keyframes waveSwell {\n  0%   { transform: translateX(0) scaleY(1); }\n  50%  { transform: translateX(-18px) scaleY(1.18); }\n  100% { transform: translateX(0) scaleY(1); }\n}\n@keyframes waveShift {\n  0%   { transform: translateX(0) scaleY(1); }\n  50%  { transform: translateX(22px) scaleY(0.88); }\n  100% { transform: translateX(0) scaleY(1); }\n}\n@keyframes foamFloat {\n  0%   { transform: translateY(0) scale(1); opacity: 0.7; }\n  50%  { transform: translateY(-6px) scale(1.12); opacity: 1; }\n  100% { transform: translateY(0) scale(1); opacity: 0.7; }\n}\n@keyframes sunGlow {\n  0%   { box-shadow: 0 0 10px 4px #f0d898, 0 0 0 0 #e8c870; }\n  50%  { box-shadow: 0 0 18px 8px #f0d898, 0 0 28px 10px #e8c87044; }\n  100% { box-shadow: 0 0 10px 4px #f0d898, 0 0 0 0 #e8c870; }\n}\n\n.demo-stage {\n  width: 200px;\n  height: 200px;\n  position: relative;\n  overflow: hidden;\n  background: linear-gradient(180deg, #d4e8f4 0%, #b8d8ee 45%, #a8cce4 100%);\n}\n\n/* 太陽 */\n.demo-stage .sun {\n  position: absolute;\n  top: 18px;\n  left: 50%;\n  transform: translateX(-50%);\n  width: 32px;\n  height: 32px;\n  border-radius: 50%;\n  background: radial-gradient(circle, #f8e888 60%, #e8c870 100%);\n  box-shadow: 0 0 10px 4px #f0d898;\n  animation: sunGlow 4s ease-in-out infinite;\n}\n\n/* 遠景の小さな波 */\n.demo-stage .wave-far {\n  position: absolute;\n  bottom: 82px;\n  left: -20px;\n  width: 240px;\n  height: 28px;\n  border-radius: 50% 50% 0 0 / 100% 100% 0 0;\n  background: linear-gradient(180deg, #90b8d8 0%, #78a8cc 100%);\n  opacity: 0.6;\n  animation: waveShift 5s ease-in-out infinite;\n}\n\n/* 中景の波 */\n.demo-stage .wave-mid {\n  position: absolute;\n  bottom: 62px;\n  left: -30px;\n  width: 260px;\n  height: 40px;\n  border-radius: 50% 50% 0 0 / 100% 100% 0 0;\n  background: linear-gradient(180deg, #78b0d0 0%, #60a0c4 100%);\n  opacity: 0.8;\n  animation: waveSwell 4s ease-in-out infinite;\n}\n.demo-stage .wave-mid::before {\n  content: '';\n  position: absolute;\n  top: -10px;\n  left: 60px;\n  width: 80px;\n  height: 20px;\n  border-radius: 50%;\n  background: rgba(255,255,255,0.28);\n}\n\n/* 主役の波 */\n.demo-stage .wave-main {\n  position: absolute;\n  bottom: 36px;\n  left: -40px;\n  width: 280px;\n  height: 64px;\n  border-radius: 50% 50% 0 0 / 100% 100% 0 0;\n  background: linear-gradient(180deg, #5898c0 0%, #4888b4 60%, #3878a8 100%);\n  animation: waveSwell 3.5s ease-in-out infinite;\n}\n.demo-stage .wave-main::before {\n  content: '';\n  position: absolute;\n  top: -14px;\n  left: 30px;\n  width: 120px;\n  height: 28px;\n  border-radius: 50% 60% 40% 50% / 60% 50% 50% 40%;\n  background: rgba(255,255,255,0.35);\n  animation: foamFloat 3.5s ease-in-out infinite;\n}\n.demo-stage .wave-main::after {\n  content: '';\n  position: absolute;\n  top: -8px;\n  right: 40px;\n  width: 60px;\n  height: 16px;\n  border-radius: 50%;\n  background: rgba(255,255,255,0.22);\n  animation: foamFloat 3.5s ease-in-out infinite 0.6s;\n}\n\n/* 前景の波（海底） */\n.demo-stage .wave-front {\n  position: absolute;\n  bottom: 0;\n  left: -20px;\n  width: 240px;\n  height: 50px;\n  border-radius: 50% 50% 0 0 / 100% 100% 0 0;\n  background: linear-gradient(180deg, #3878a8 0%, #2d6898 100%);\n  animation: waveShift 3s ease-in-out infinite;\n}\n\n/* 泡1 */\n.demo-stage .foam-1 {\n  position: absolute;\n  bottom: 48px;\n  left: 30px;\n  width: 12px;\n  height: 8px;\n  border-radius: 50%;\n  background: rgba(255,255,255,0.55);\n  animation: foamFloat 2.5s ease-in-out infinite 0.3s;\n}\n/* 泡2 */\n.demo-stage .foam-2 {\n  position: absolute;\n  bottom: 52px;\n  left: 70px;\n  width: 8px;\n  height: 6px;\n  border-radius: 50%;\n  background: rgba(255,255,255,0.45);\n  animation: foamFloat 3s ease-in-out infinite 1s;\n}\n/* 泡3 */\n.demo-stage .foam-3 {\n  position: absolute;\n  bottom: 46px;\n  left: 140px;\n  width: 10px;\n  height: 7px;\n  border-radius: 50%;\n  background: rgba(255,255,255,0.5);\n  animation: foamFloat 2.8s ease-in-out infinite 0.7s;\n}",
    "demo_html": "<div class=\"demo-stage\">\n  <div class=\"sun\"></div>\n  <div class=\"wave-far\"></div>\n  <div class=\"wave-mid\"></div>\n  <div class=\"wave-main\"></div>\n  <div class=\"foam-1\"></div>\n  <div class=\"foam-2\"></div>\n  <div class=\"foam-3\"></div>\n  <div class=\"wave-front\"></div>\n</div>"
  },
  {
    "date": "2026-07-15",
    "theme": "炎",
    "title": "揺れる炎",
    "keyframes_css": "@keyframes flameMain {\n  0%   { transform: scaleX(1)   scaleY(1)   translateY(0px);  border-radius: 50% 50% 30% 30% / 60% 60% 40% 40%; }\n  25%  { transform: scaleX(0.88) scaleY(1.06) translateY(-3px); border-radius: 55% 45% 28% 32% / 62% 58% 42% 38%; }\n  50%  { transform: scaleX(1.08) scaleY(0.97) translateY(2px);  border-radius: 45% 55% 32% 28% / 58% 62% 38% 42%; }\n  75%  { transform: scaleX(0.93) scaleY(1.04) translateY(-2px); border-radius: 52% 48% 30% 30% / 60% 60% 40% 40%; }\n  100% { transform: scaleX(1)   scaleY(1)   translateY(0px);  border-radius: 50% 50% 30% 30% / 60% 60% 40% 40%; }\n}\n\n@keyframes flameMid {\n  0%   { transform: scaleX(1)   scaleY(1)   translateY(0px) rotate(-1deg); }\n  33%  { transform: scaleX(0.85) scaleY(1.08) translateY(-4px) rotate(2deg); }\n  66%  { transform: scaleX(1.1)  scaleY(0.95) translateY(2px)  rotate(-2deg); }\n  100% { transform: scaleX(1)   scaleY(1)   translateY(0px) rotate(-1deg); }\n}\n\n@keyframes flameTip {\n  0%   { transform: scaleX(1)   scaleY(1)   translateY(0px) rotate(0deg);  opacity: 0.85; }\n  30%  { transform: scaleX(0.78) scaleY(1.12) translateY(-6px) rotate(3deg);  opacity: 1; }\n  60%  { transform: scaleX(1.15) scaleY(0.92) translateY(3px)  rotate(-3deg); opacity: 0.75; }\n  100% { transform: scaleX(1)   scaleY(1)   translateY(0px) rotate(0deg);  opacity: 0.85; }\n}\n\n@keyframes emberFloat {\n  0%   { transform: translate(0px, 0px) scale(1);   opacity: 0.9; }\n  50%  { transform: translate(4px, -18px) scale(0.7); opacity: 0.6; }\n  100% { transform: translate(-2px, -36px) scale(0.3); opacity: 0; }\n}\n\n@keyframes glowPulse {\n  0%   { opacity: 0.35; transform: scale(1); }\n  50%  { opacity: 0.55; transform: scale(1.06); }\n  100% { opacity: 0.35; transform: scale(1); }\n}\n\n@keyframes logRock {\n  0%   { transform: rotate(-1deg); }\n  50%  { transform: rotate(1deg); }\n  100% { transform: rotate(-1deg); }\n}\n\n.demo-stage {\n  width: 200px;\n  height: 200px;\n  position: relative;\n  overflow: hidden;\n  background: linear-gradient(170deg, #ececea 0%, #e4e2de 60%, #dedad4 100%);\n}\n\n/* 地面 */\n.demo-stage .ground {\n  position: absolute;\n  bottom: 0;\n  left: 0;\n  width: 100%;\n  height: 38px;\n  background: linear-gradient(180deg, #cec8be 0%, #bfb9ae 100%);\n  border-radius: 0;\n}\n\n/* 薪 左 */\n.demo-stage .log-left {\n  position: absolute;\n  bottom: 26px;\n  left: 58px;\n  width: 56px;\n  height: 14px;\n  background: linear-gradient(180deg, #b09070 0%, #8a6a50 100%);\n  border-radius: 7px;\n  transform: rotate(-18deg);\n  box-shadow: 0 2px 4px rgba(100,70,40,0.3);\n  animation: logRock 5s ease-in-out infinite;\n}\n\n/* 薪 右 */\n.demo-stage .log-right {\n  position: absolute;\n  bottom: 26px;\n  left: 90px;\n  width: 56px;\n  height: 14px;\n  background: linear-gradient(180deg, #b09070 0%, #8a6a50 100%);\n  border-radius: 7px;\n  transform: rotate(18deg);\n  box-shadow: 0 2px 4px rgba(100,70,40,0.3);\n  animation: logRock 5s ease-in-out infinite reverse;\n}\n\n/* 炎 底部（もっとも明るいオレンジ） */\n.demo-stage .flame-base {\n  position: absolute;\n  bottom: 34px;\n  left: 50%;\n  transform: translateX(-50%);\n  width: 72px;\n  height: 72px;\n  background: radial-gradient(ellipse at 50% 80%, #f0c070 0%, #e8903a 55%, #d06020 100%);\n  border-radius: 50% 50% 30% 30% / 60% 60% 40% 40%;\n  box-shadow: 0 0 18px 6px rgba(230,140,50,0.45);\n  animation: flameMain 2.4s cubic-bezier(0.45, 0.05, 0.55, 0.95) infinite;\n}\n\n/* 炎 中段（やや赤みを帯びた橙） */\n.demo-stage .flame-mid {\n  position: absolute;\n  bottom: 62px;\n  left: 50%;\n  transform: translateX(-50%);\n  width: 50px;\n  height: 62px;\n  background: radial-gradient(ellipse at 50% 75%, #f0a850 0%, #d86030 60%, #c04020 100%);\n  border-radius: 50% 50% 30% 30% / 65% 65% 35% 35%;\n  box-shadow: 0 0 12px 4px rgba(210,100,40,0.35);\n  animation: flameMid 1.9s cubic-bezier(0.4, 0.0, 0.6, 1.0) infinite;\n  animation-delay: -0.3s;\n}\n\n/* 炎 先端（赤みが強い） */\n.demo-stage .flame-tip {\n  position: absolute;\n  bottom: 108px;\n  left: 50%;\n  transform: translateX(-50%);\n  width: 28px;\n  height: 46px;\n  background: radial-gradient(ellipse at 50% 70%, #e88050 0%, #c84030 55%, #a02820 100%);\n  border-radius: 50% 50% 30% 30% / 70% 70% 30% 30%;\n  opacity: 0.85;\n  animation: flameTip 1.5s cubic-bezier(0.3, 0.0, 0.7, 1.0) infinite;\n  animation-delay: -0.6s;\n}\n\n/* 炎 先端の光芒 */\n.demo-stage .flame-tip::after {\n  content: '';\n  position: absolute;\n  top: 4px;\n  left: 50%;\n  transform: translateX(-50%);\n  width: 10px;\n  height: 20px;\n  background: radial-gradient(ellipse at 50% 60%, #f8d090 0%, transparent 80%);\n  border-radius: 50%;\n  opacity: 0.7;\n}\n\n/* 光のにじみ（グロー） */\n.demo-stage .glow {\n  position: absolute;\n  bottom: 20px;\n  left: 50%;\n  transform: translateX(-50%);\n  width: 110px;\n  height: 80px;\n  background: radial-gradient(ellipse at 50% 70%, rgba(240,170,60,0.55) 0%, rgba(220,120,40,0.2) 55%, transparent 80%);\n  border-radius: 50%;\n  animation: glowPulse 2.4s ease-in-out infinite;\n}\n\n/* 火の粉 1 */\n.demo-stage .ember-1 {\n  position: absolute;\n  bottom: 100px;\n  left: 96px;\n  width: 5px;\n  height: 5px;\n  background: #f0b040;\n  border-radius: 50%;\n  box-shadow: 0 0 4px 1px rgba(240,170,50,0.7);\n  animation: emberFloat 2.2s ease-in infinite;\n  animation-delay: 0s;\n}\n\n/* 火の粉 2 */\n.demo-stage .ember-2 {\n  position: absolute;\n  bottom: 90px;\n  left: 112px;\n  width: 4px;\n  height: 4px;\n  background: #e89040;\n  border-radius: 50%;\n  box-shadow: 0 0 3px 1px rgba(230,150,50,0.6);\n  animation: emberFloat 2.8s ease-in infinite;\n  animation-delay: -0.9s;\n}\n\n/* 火の粉 3 */\n.demo-stage .ember-3 {\n  position: absolute;\n  bottom: 95px;\n  left: 80px;\n  width: 3px;\n  height: 3px;\n  background: #f0c060;\n  border-radius: 50%;\n  box-shadow: 0 0 3px 1px rgba(240,180,60,0.6);\n  animation: emberFloat 3.2s ease-in infinite;\n  animation-delay: -1.8s;\n}",
    "demo_html": "<div class=\"demo-stage\">\n  <div class=\"glow\"></div>\n  <div class=\"flame-tip\"></div>\n  <div class=\"flame-mid\"></div>\n  <div class=\"flame-base\"></div>\n  <div class=\"ember-1\"></div>\n  <div class=\"ember-2\"></div>\n  <div class=\"ember-3\"></div>\n  <div class=\"log-left\"></div>\n  <div class=\"log-right\"></div>\n  <div class=\"ground\"></div>\n</div>"
  }
]